lightopic/__init__.py
lightopic/_lightopic.py
lightopic/_version.py
lightopic/lightbertopic.py
lightopic-0.0.6.dist-info/METADATA
lightopic-0.0.6.dist-info/WHEEL
lightopic-0.0.6.dist-info/top_level.txt
lightopic-0.0.6.dist-info/RECORD
