Metadata-Version: 2.1
Name: lightopic
Version: 0.0.6
Summary: Slimmer version of BERTopic for transforming new data with an existing, trained model.
Author-email: Hamed Bastan-Hagh <hamed@bastanhagh.com>
Project-URL: Repository, https://github.com/hamedbh/lightopic/
Project-URL: Issues, https://github.com/hamedbh/lightopic/issues
Project-URL: Documentation, https://lightopic.readthedocs.io/en/stable/index.html
Classifier: License :: OSI Approved :: MIT License
Requires-Python: >=3.10
Requires-Dist: hdbscan >=0.8.39
Requires-Dist: joblib >=1.4.2
Requires-Dist: numba >=0.59.0
Requires-Dist: numpy >=2.0.2
Requires-Dist: umap-learn >=0.5.7
Provides-Extra: bertopic
Requires-Dist: bertopic >=0.16.4 ; extra == 'bertopic'
Provides-Extra: dev
Requires-Dist: bertopic >=0.16.4 ; extra == 'dev'
Requires-Dist: build >=1.2.2.post1 ; extra == 'dev'
Requires-Dist: myst-nb >=1.1.2 ; extra == 'dev'
Requires-Dist: pre-commit >=4.0.1 ; extra == 'dev'
Requires-Dist: pytest >=8.3.3 ; extra == 'dev'
Requires-Dist: ruff >=0.7.4 ; extra == 'dev'
Requires-Dist: sphinx >=8.1.3 ; extra == 'dev'
Requires-Dist: sphinx-autoapi >=3.3.3 ; extra == 'dev'
Requires-Dist: sphinx-rtd-theme >=3.0.2 ; extra == 'dev'
Requires-Dist: setuptools-scm >=8.1.0 ; extra == 'dev'
